cutewindow/Icon.py
cutewindow/__init__.py
cutewindow/base.py
cutewindow/platform_factory.py
cutewindow/platforms/__init__.py
cutewindow/platforms/mac/CuteDialog.py
cutewindow/platforms/mac/CuteMainWindow.py
cutewindow/platforms/mac/CuteWindow.py
cutewindow/platforms/mac/__init__.py
cutewindow/platforms/mac/title_bar/TitleBar.py
cutewindow/platforms/mac/utils.py
cutewindow/platforms/windows/CuteDialog.py
cutewindow/platforms/windows/CuteMainWindow.py
cutewindow/platforms/windows/CuteWindow.py
cutewindow/platforms/windows/__init__.py
cutewindow/platforms/windows/c_structures.py
cutewindow/platforms/windows/native_event.py
cutewindow/platforms/windows/title_bar/TitleBar.py
cutewindow/platforms/windows/title_bar/resources.qrc
cutewindow/platforms/windows/title_bar/resources_rc.py
cutewindow/platforms/windows/title_bar/title-bar/close.png
cutewindow/platforms/windows/title_bar/title-bar/close@2x.png
cutewindow/platforms/windows/title_bar/title-bar/close@3x.png
cutewindow/platforms/windows/title_bar/title-bar/maximize.png
cutewindow/platforms/windows/title_bar/title-bar/maximize@2x.png
cutewindow/platforms/windows/title_bar/title-bar/maximize@3x.png
cutewindow/platforms/windows/title_bar/title-bar/minimize.png
cutewindow/platforms/windows/title_bar/title-bar/minimize@2x.png
cutewindow/platforms/windows/title_bar/title-bar/minimize@3x.png
cutewindow/platforms/windows/title_bar/title-bar/restore.png
cutewindow/platforms/windows/title_bar/title-bar/restore@2x.png
cutewindow/platforms/windows/title_bar/title-bar/restore@3x.png
cutewindow/platforms/windows/utils.py
pyside6_cutewindow-0.1.1.dist-info/METADATA
pyside6_cutewindow-0.1.1.dist-info/WHEEL
pyside6_cutewindow-0.1.1.dist-info/licenses/LICENSE
pyside6_cutewindow-0.1.1.dist-info/RECORD
