Metadata-Version: 2.4
Name: pyside6-cutewindow
Version: 0.1.1
Summary: Cross-platform customizable window library based on PySide6 with enhanced control
License: MIT
License-File: LICENSE
Keywords: qt,pyqt,pyqt6,pyqt5,pyside,pyside2,pyside6,customizable-window,cross-platform,gui,window-customization,pyside6-cutewindow
Author: Parham Oyan
Author-email: parhamoyan@yahoo.com
Requires-Python: >=3.9,<3.14
Classifier: Development Status :: 4 - Beta
Classifier: Intended Audience :: Developers
Classifier: License :: OSI Approved :: MIT License
Classifier: Operating System :: OS Independent
Classifier: Programming Language :: Python :: 3
Classifier: Programming Language :: Python :: 3.9
Classifier: Programming Language :: Python :: 3.10
Classifier: Programming Language :: Python :: 3.11
Classifier: Programming Language :: Python :: 3.12
Classifier: Programming Language :: Python :: 3.13
Classifier: Topic :: Software Development :: Libraries :: Python Modules
Classifier: Topic :: Software Development :: User Interfaces
Requires-Dist: PySide6 (>=6.0.0)
Requires-Dist: pyobjc-framework-Cocoa (>=9.0.1) ; sys_platform == "darwin"
Requires-Dist: pyobjc-framework-Quartz ; sys_platform == "darwin"
Requires-Dist: pywin32 (>=304) ; sys_platform == "win32"
Project-URL: Bug Tracker, https://github.com/parhamoyan/cutewindow/issues
Project-URL: Changelog, https://github.com/parhamoyan/cutewindow/blob/main/CHANGELOG.md
Project-URL: Documentation, https://pyside6-cutewindow.readthedocs.io
Project-URL: Repository, https://github.com/parhamoyan/cutewindow
Project-URL: Source, https://github.com/parhamoyan/cutewindow
